pyweste/__init__.py
pyweste/core.py
pyweste/reg.py
pyweste/uins.py
pyweste/utils.py
pyweste-0.0.4.dist-info/METADATA
pyweste-0.0.4.dist-info/WHEEL
pyweste-0.0.4.dist-info/licenses/LICENSE
pyweste-0.0.4.dist-info/RECORD
