Metadata-Version: 2.4
Name: pyweste
Version: 0.0.4
Summary: An Extra / Helper package for PyWest (Main Package)
Author: qyct
License: Apache-2.0
License-File: LICENSE
Requires-Python: >=3.11
Requires-Dist: dearpygui
Requires-Dist: pillow
Requires-Dist: pywin32
